text/__init__.py
text/filters.py
uf_text/__init__.py
uf_text/filters.py
util_func-0.0.2.dist-info/LICENSE
util_func-0.0.2.dist-info/METADATA
util_func-0.0.2.dist-info/WHEEL
util_func-0.0.2.dist-info/top_level.txt
util_func-0.0.2.dist-info/RECORD
